{
  "patient": {
    "name": "Baha",
    "gender": "Male",
    "age": "N/A",
    "nationality": "Saudi",
    "ID": "N/A"
  },
  "scene": {
    "date": "N/A",
    "time": "N/A",
    "caller_phone": "N/A",
    "location": "N/A",
    "case_code": "N/A",
    "case_type": "Medical",
    "mechanism": "Other"
  },
  "chief_complaint": "Seizures and severe relapse",
  "history": {
    "onset": "In the evening",
    "duration": "1 hour",
    "associated_symptoms": [
      "migraines",
      "lack of sleep"
    ],
    "allergies": "sense of taste",
    "medications": "N/A",
    "past_history": "N/A",
    "last_meal": "N/A",
    "events": "N/A"
  },
  "vitals": {
    "bp_systolic": 120,
    "bp_diastolic": 70,
    "hr": null,
    "rr": null,
    "spo2": null,
    "temp": null,
    "gcs": null,
    "pain_scale_0_10": null
  },
  "exam": "N/A",
  "interventions": [
    "Monitor vitals",
    "Provide reassurance"
  ],
  "severity": "High",
  "recommendation": "Transfer to hospital",
  "reasoning": "Patient has a history of seizures and severe relapse, indicating potential risk.",
  "form_en": "==== PATIENT INFO ====\nName              : Baha\nGender            : Male\nAge               : N/A\nNationality       : Saudi\nID                : N/A\n\n==== SCENE DETAILS ====\nDate              : N/A\nTime              : N/A\nCaller Phone      : N/A\nLocation          : N/A\nCase Code         : N/A\nCase Type         : Medical\nMechanism         : Other\n\n==== CHIEF COMPLAINT ====\nSeizures and severe relapse\n\n==== HISTORY (SAMPLE) ====\nOnset             : In the evening\nDuration          : 1 hour\nAssociated Sx     : migraines, lack of sleep\nAllergies         : sense of taste\nMedications       : N/A\nPast History      : N/A\nLast Meal         : N/A\nEvents            : N/A\n\n==== VITALS ====\nBP (Sys/Dia)      : 120/70\nHeart Rate        : N/A\nResp Rate         : N/A\nSpO2              : N/A\nTemperature       : N/A\nGCS               : N/A\nPain (0-10)       : N/A\n\n==== EXAM FINDINGS ====\nN/A\n\n==== INTERVENTIONS ====\n- Monitor vitals\n- Provide reassurance\n\n==== SEVERITY & ACTION ====\nSeverity          : High\nRecommendation    : Transfer to hospital\nReasoning         : Patient has a history of seizures and severe relapse, indicating potential risk."
}